rmvrarith1/__init__.py
rmvrarith1/calculator.py
rmvrarith1-0.1.0.dist-info/licenses/LICENSE.txt
rmvrarith1-0.1.0.dist-info/METADATA
rmvrarith1-0.1.0.dist-info/WHEEL
rmvrarith1-0.1.0.dist-info/top_level.txt
rmvrarith1-0.1.0.dist-info/RECORD
